{
  "id": "fb401f2e-e726-467a-aaee-03f94f3f5244",
  "prevId": "00000000-0000-0000-0000-000000000000",
  "version": "7",
  "dialect": "postgresql",
  "tables": {
    "public.dsc_user": {
      "name": "dsc_user",
      "schema": "",
      "columns": {
        "id": {
          "name": "id",
          "type": "text",
          "primaryKey": true,
          "notNull": true
        },
        "username": {
          "name": "username",
          "type": "text",
          "primaryKey": false,
          "notNull": true
        },
        "channelId": {
          "name": "channelId",
          "type": "text",
          "primaryKey": false,
          "notNull": false
        }
      },
      "indexes": {},
      "foreignKeys": {},
      "compositePrimaryKeys": {},
      "uniqueConstraints": {
        "dsc_user_id_unique": {
          "name": "dsc_user_id_unique",
          "nullsNotDistinct": false,
          "columns": [
            "id"
          ]
        },
        "dsc_user_username_unique": {
          "name": "dsc_user_username_unique",
          "nullsNotDistinct": false,
          "columns": [
            "username"
          ]
        }
      }
    },
    "public.tv_account": {
      "name": "tv_account",
      "schema": "",
      "columns": {
        "dsc_user_id": {
          "name": "dsc_user_id",
          "type": "text",
          "primaryKey": false,
          "notNull": true
        },
        "username": {
          "name": "username",
          "type": "text",
          "primaryKey": false,
          "notNull": true
        },
        "password": {
          "name": "password",
          "type": "text",
          "primaryKey": false,
          "notNull": true
        },
        "backup_code": {
          "name": "backup_code",
          "type": "text",
          "primaryKey": false,
          "notNull": true
        },
        "cookies": {
          "name": "cookies",
          "type": "text",
          "primaryKey": false,
          "notNull": false
        }
      },
      "indexes": {
        "user_idx": {
          "name": "user_idx",
          "columns": [
            {
              "expression": "dsc_user_id",
              "isExpression": false,
              "asc": true,
              "nulls": "last"
            }
          ],
          "isUnique": false,
          "concurrently": false,
          "method": "btree",
          "with": {}
        },
        "username_idx": {
          "name": "username_idx",
          "columns": [
            {
              "expression": "dsc_user_id",
              "isExpression": false,
              "asc": true,
              "nulls": "last"
            }
          ],
          "isUnique": false,
          "concurrently": false,
          "method": "btree",
          "with": {}
        }
      },
      "foreignKeys": {
        "tv_account_dsc_user_id_dsc_user_id_fk": {
          "name": "tv_account_dsc_user_id_dsc_user_id_fk",
          "tableFrom": "tv_account",
          "tableTo": "dsc_user",
          "columnsFrom": [
            "dsc_user_id"
          ],
          "columnsTo": [
            "id"
          ],
          "onDelete": "no action",
          "onUpdate": "no action"
        }
      },
      "compositePrimaryKeys": {},
      "uniqueConstraints": {
        "tv_account_dsc_user_id_unique": {
          "name": "tv_account_dsc_user_id_unique",
          "nullsNotDistinct": false,
          "columns": [
            "dsc_user_id"
          ]
        }
      }
    }
  },
  "enums": {},
  "schemas": {},
  "_meta": {
    "columns": {},
    "schemas": {},
    "tables": {}
  }
}